CHANGELOG.txt
LICENCE.txt
MANIFEST.in
README.txt
setup.py
Harish_kumar.egg-info/SOURCES.txt
Harish_kumar.egg-info/dependency_links.txt
Harish_kumar.egg-info/top_level.txt
harishpyRestring.egg-info/PKG-INFO
harishpyRestring.egg-info/SOURCES.txt
harishpyRestring.egg-info/dependency_links.txt
harishpyRestring.egg-info/top_level.txt
joshbasiccalculator/__init__.py