Metadata-Version: 1.1
Name: harishpyRestring
Version: 0.0.1
Summary: A very basic string Formatting Function
Home-page: UNKNOWN
Author: harishkumar
Author-email: harishkamamala0909@gmail.com
License: MIT
Keywords: stringReplace
Platform: UNKNOWN
Classifier: Development Status :: 5 - Production/Stable
Classifier: Intended Audience :: Education
Classifier: Operating System :: Microsoft :: Windows :: Windows 10
Classifier: License :: OSI Approved :: MIT License
Classifier: Programming Language :: Python :: 3
